striacli.py
stria.cpython-35m-x86_64-linux-gnu.so
stria-0.1.3.dist-info/RECORD
stria-0.1.3.dist-info/METADATA
stria-0.1.3.dist-info/top_level.txt
stria-0.1.3.dist-info/WHEEL
stria-0.1.3.dist-info/LICENSE
stria-0.1.3.dist-info/entry_points.txt
