Metadata-Version: 2.1
Name: stria
Version: 0.1.3
Summary: stria (short tandem repeat identification and analysis) is a python package for finding tandem repeats from DNA sequences
Home-page: https://github.com/lmdu/stria
Author: Lianming Du
Author-email: adullb@qq.com
License: MIT
Keywords: bioinformatics microsatellite tandem repeats
Platform: UNKNOWN
Classifier: Development Status :: 5 - Production/Stable
Classifier: Intended Audience :: Developers
Classifier: Intended Audience :: Education
Classifier: Intended Audience :: Science/Research
Classifier: Natural Language :: English
Classifier: License :: OSI Approved :: MIT License
Classifier: Programming Language :: C
Classifier: Programming Language :: Python :: 3.5
Classifier: Programming Language :: Python :: 3.6
Classifier: Programming Language :: Python :: 3.7
Classifier: Programming Language :: Python :: 3.8
Classifier: Programming Language :: Python :: 3.9
Classifier: Operating System :: Microsoft :: Windows
Classifier: Operating System :: POSIX :: Linux
Classifier: Operating System :: Unix
Classifier: Topic :: Scientific/Engineering :: Bio-Informatics
